[{"sentence": "\u201c\u9b54\u6539\u7248\u201dT-90\u6765\u4e86\uff1a\u4fc4\u519b\u6b63\u5f0f\u5217\u88c5T-90M\u4e3b\u6218\u5766\u514b", "events": [{"trigger": {"text": "\u5217\u88c5", "offset": 16, "length": 2}, "object": {"text": "", "offset": 0, "length": 0}, "subject": {"text": "\u4fc4\u519b", "offset": 12, "length": 2}, "labels": {"tense": "\u73b0\u5728", "polarity": "\u80af\u5b9a"}}], "arguments": {"time": [], "loc": [], "country": [{"text": "\u4fc4", "offset": 12, "length": 1}], "weapon": [{"text": "T-90M\u4e3b\u6218\u5766\u514b", "offset": 18, "length": 9}]}}, {"sentence": "\u3010\u73af\u7403\u7f51\u519b\u4e8b\u62a5\u9053\u3011", "events": [], "arguments": {"time": [], "loc": [], "country": [], "weapon": []}}, {"sentence": "\u4fc4\u7f57\u65af\u536b\u661f\u901a\u8baf\u793e4\u670813\u65e5\u62a5\u9053\uff0c\u4fc4\u7f57\u65af\u897f\u90e8\u519b\u533a\u65b0\u95fb\u5904\u53d1\u5e03\u6d88\u606f\u8868\u793a\uff0c\u4fc4\u519b4\u6708\u5df2\u63a5\u88c5\u9996\u6279\u6539\u8fdb\u578bT-90M\u201c\u7a81\u7834\u201d\u5766\u514b\u3002", "events": [{"trigger": {"text": "\u63a5\u88c5", "offset": 38, "length": 2}, "object": {"text": "", "offset": 0, "length": 0}, "subject": {"text": "\u4fc4\u519b", "offset": 33, "length": 2}, "labels": {"tense": "\u8fc7\u53bb", "polarity": "\u80af\u5b9a"}}, {"trigger": {"text": "\u6539\u8fdb", "offset": 42, "length": 2}, "object": {"text": "", "offset": 0, "length": 0}, "subject": {"text": "\u4fc4\u519b", "offset": 33, "length": 2}, "labels": {"tense": "\u8fc7\u53bb", "polarity": "\u80af\u5b9a"}}], "arguments": {"time": [{"text": "4\u6708", "offset": 35, "length": 2}, {"text": "4\u670813\u65e5", "offset": 8, "length": 5}], "loc": [], "country": [{"text": "\u4fc4\u7f57\u65af", "offset": 16, "length": 3}, {"text": "\u4fc4\u7f57\u65af", "offset": 0, "length": 3}], "weapon": [{"text": "T-90M\u201c\u7a81\u7834\u201d\u5766\u514b", "offset": 45, "length": 11}]}}, {"sentence": "\u4fc4\u897f\u90e8\u519b\u533a\u7b2c\u4e00\u5766\u514b\u96c6\u56e2\u519b\u53f8\u4ee4\u8c22\u5c14\u76d6\u00b7\u57fa\u585e\u5c14\u4e2d\u5c064\u670813\u65e5\u8868\u793a\uff1a\u201c\u6570\u8f86T-90M\u5766\u514b\u5df2\u4e8e4\u6708\u5217\u88c5\u5854\u66fc\u6469\u6b65\u5e08\u3002", "events": [{"trigger": {"text": "\u5217\u88c5", "offset": 45, "length": 2}, "object": {"text": "", "offset": 0, "length": 0}, "subject": {"text": "", "offset": 0, "length": 0}, "labels": {"tense": "\u5176\u4ed6", "polarity": "\u53ef\u80fd"}}], "arguments": {"time": [{"text": "4\u670813\u65e5", "offset": 23, "length": 5}, {"text": "4\u6708", "offset": 43, "length": 2}], "loc": [], "country": [{"text": "\u4fc4", "offset": 0, "length": 1}], "weapon": [{"text": "T-90M\u5766\u514b", "offset": 34, "length": 7}]}}, {"sentence": "\u8fd9\u662f\u5168\u65b0\u4f5c\u6218\u8f66\u8f86\uff0c\u5b83\u5177\u6709\u65b0\u578b\u70ae\u5854\u3001\u529f\u7387\u66f4\u5927\u7684\u53d1\u52a8\u673a\u3002", "events": [], "arguments": {"time": [], "loc": [], "country": [], "weapon": [{"text": "\u4f5c\u6218\u8f66\u8f86", "offset": 4, "length": 4}]}}, {"sentence": "\u8be5\u5766\u514b\u88c5\u5907\u6709\u65b0\u578b\u591a\u8def\u7784\u51c6\u5177\uff0c\u8fd9\u53ef\u4ee5\u5728\u4e00\u5929\u4efb\u4f55\u65f6\u95f4\u4f7f\u7528\u6b66\u5668\u3002", "events": [], "arguments": {"time": [], "loc": [], "country": [], "weapon": [{"text": "\u5766\u514b", "offset": 1, "length": 2}]}}, {"sentence": "\u201d", "events": [], "arguments": {"time": [], "loc": [], "country": [], "weapon": []}}, {"sentence": "\u4ed6\u8865\u5145\u8bf4\uff0c\u6539\u8fdb\u578bT-90M\u5766\u514b\u7684\u4e00\u4e2a\u4e3b\u8981\u7279\u6027\u662f\u80fd\u591f\u4e0e\u5176\u4ed6\u8f66\u8f86\u5b9e\u65f6\u4ea4\u6362\u6570\u636e\u3002", "events": [], "arguments": {"time": [], "loc": [], "country": [], "weapon": [{"text": "\u6539\u8fdb\u578bT-90M\u5766\u514b", "offset": 5, "length": 10}]}}, {"sentence": "T-90M\u662f\u4fc4\u5236T-90\u5766\u514b\u6700\u65b0\u7248\u672c\uff0c\u88ab\u79f0\u4e3a\u201c\u9b54\u6539\u7248\u201dT-90\u5766\u514b\u3002", "events": [], "arguments": {"time": [], "loc": [], "country": [{"text": "\u4fc4", "offset": 6, "length": 1}], "weapon": [{"text": "T-90\u5766\u514b", "offset": 27, "length": 6}, {"text": "T-90M", "offset": 0, "length": 5}, {"text": "T-90\u5766\u514b", "offset": 8, "length": 6}, {"text": "\u201c\u9b54\u6539\u7248\u201dT-90\u5766\u514b", "offset": 22, "length": 11}]}}, {"sentence": "\u5728\u4fc4\u5236\u6700\u5148\u8fdb\u7684T-14\u201c\u963f\u739b\u5854\u201d\u5766\u514b\u6280\u672f\u5c1a\u672a\u6210\u719f\u3001\u672a\u80fd\u5927\u6279\u91cf\u5217\u88c5\u4e4b\u9645\uff0cT-90M\u5766\u514b\u5c06\u79f0\u4e3a\u4fc4\u4e24\u4ee3\u5766\u514b\u4e4b\u95f4\u7684\u8fc7\u6e21\u4ea7\u54c1\uff0c\u5f25\u8865\u6218\u529b\u7a7a\u7f3a\u3002", "events": [{"trigger": {"text": "\u5217\u88c5", "offset": 30, "length": 2}, "object": {"text": "", "offset": 0, "length": 0}, "subject": {"text": "", "offset": 0, "length": 0}, "labels": {"tense": "\u5176\u4ed6", "polarity": "\u53ef\u80fd"}}], "arguments": {"time": [], "loc": [], "country": [{"text": "\u4fc4", "offset": 45, "length": 1}], "weapon": [{"text": "T-14\u201c\u963f\u739b\u5854\u201d\u5766\u514b", "offset": 7, "length": 11}, {"text": "T-90M\u5766\u514b", "offset": 35, "length": 7}]}}, {"sentence": "\u4e0e\u666e\u901a\u7248\u7684T-90\u5766\u514b\u76f8\u6bd4\uff0cT-90M\u5766\u514b\u6362\u88c5\u4e86\u65b0\u578b\u7684\u7206\u70b8\u53cd\u5e94\u88c5\u7532\u3001\u70ae\u5854\u4e0b\u65b9\u52a0\u88c5\u4e86\u94fe\u7532\u5f0f\u88c5\u7532\uff0c\u53ef\u8fdb\u4e00\u6b65\u589e\u5f3a\u5bf9RPG\u706b\u7bad\u5f39\u7b49\u6b66\u5668\u7684\u6253\u51fb\u3002", "events": [{"trigger": {"text": "\u7206\u70b8", "offset": 27, "length": 2}, "object": {"text": "", "offset": 0, "length": 0}, "subject": {"text": "", "offset": 0, "length": 0}, "labels": {"tense": "\u5176\u4ed6", "polarity": "\u53ef\u80fd"}}, {"trigger": {"text": "\u6253\u51fb", "offset": 64, "length": 2}, "object": {"text": "", "offset": 0, "length": 0}, "subject": {"text": "", "offset": 0, "length": 0}, "labels": {"tense": "\u5176\u4ed6", "polarity": "\u53ef\u80fd"}}], "arguments": {"time": [], "loc": [], "country": [], "weapon": [{"text": "T-90\u5766\u514b", "offset": 5, "length": 6}, {"text": "T-90M\u5766\u514b", "offset": 14, "length": 7}, {"text": "RPG\u706b\u7bad\u5f39", "offset": 54, "length": 6}]}}, {"sentence": "\u9664\u8f66\u4f53\u5916\u663e\u800c\u6613\u89c1\u7684\u5347\u7ea7\u5916\uff0cT-90M\u5766\u514b\u8f66\u5185\u7684\u7535\u5b50\u8bbe\u5907\u4e5f\u5f97\u5230\u4e86\u5927\u5e45\u5347\u7ea7\uff0c\u4fe1\u606f\u5316\u4f5c\u6218\u80fd\u529b\u8fdb\u4e00\u6b65\u589e\u5f3a\u3002", "events": [{"trigger": {"text": "\u5347\u7ea7", "offset": 33, "length": 2}, "object": {"text": "", "offset": 0, "length": 0}, "subject": {"text": "", "offset": 0, "length": 0}, "labels": {"tense": "\u5176\u4ed6", "polarity": "\u53ef\u80fd"}}], "arguments": {"time": [], "loc": [], "country": [], "weapon": [{"text": "T-90M\u5766\u514b", "offset": 13, "length": 7}]}}, {"sentence": "T-90M\u5766\u514b\u4fdd\u7559\u4e86\u539f\u6709\u7684\u201c\u7a97\u5e18\u201d\u4e3b\u52a8\u9632\u5fa1\u7cfb\u7edf\u7684\u6fc0\u5149\u68c0\u6d4b\u88c5\u7f6e\u548c\u70df\u96fe\u5f39\u53d1\u5c04\u6a21\u5757\uff0c\u800c\u62c6\u9664\u4e86\u539f\u6765\u7684\u4e3b\u52a8\u5e72\u6270\u5668\u3002", "events": [{"trigger": {"text": "\u53d1\u5c04", "offset": 34, "length": 2}, "object": {"text": "", "offset": 0, "length": 0}, "subject": {"text": "", "offset": 0, "length": 0}, "labels": {"tense": "\u5176\u4ed6", "polarity": "\u53ef\u80fd"}}], "arguments": {"time": [], "loc": [], "country": [], "weapon": [{"text": "T-90M\u5766\u514b", "offset": 0, "length": 7}]}}, {"sentence": "\u5728\u706b\u529b\u914d\u7f6e\u4e0a\uff0cT-90M\u5766\u514b\u6362\u88c5\u4e86\u4e0eT-14\u201c\u963f\u739b\u5854\u201d\u4e00\u6837\u76842A82-1M\u578b\u5766\u514b\u706b\u70ae\uff0c\u53ef\u53d1\u5c04\u65b0\u578b\u7684\u94a8\u5408\u91d1\u7a7f\u7532\u5f39\u3001\u6b21\u53e3\u5f84\u8131\u58f3\u5c3e\u7ffc\u7a33\u5b9a\u7a7f\u7532\u5f39\u30019M119M\u70ae\u5c04\u5bfc\u5f39\u7b49\uff0c\u6253\u51fb\u80fd\u529b\u8fdb\u4e00\u6b65\u63d0\u5347\u3002", "events": [{"trigger": {"text": "\u6253\u51fb", "offset": 81, "length": 2}, "object": {"text": "", "offset": 0, "length": 0}, "subject": {"text": "", "offset": 0, "length": 0}, "labels": {"tense": "\u5176\u4ed6", "polarity": "\u53ef\u80fd"}}], "arguments": {"time": [], "loc": [], "country": [], "weapon": [{"text": "2A82-1M\u578b\u5766\u514b\u706b\u70ae", "offset": 30, "length": 12}, {"text": "T-90M\u5766\u514b", "offset": 7, "length": 7}, {"text": "T-14\u201c\u963f\u739b\u5854\u201d", "offset": 18, "length": 9}, {"text": "\u94a8\u5408\u91d1\u7a7f\u7532\u5f39", "offset": 49, "length": 6}, {"text": "\u6b21\u53e3\u5f84\u8131\u58f3\u5c3e\u7ffc\u7a33\u5b9a\u7a7f\u7532\u5f39", "offset": 56, "length": 12}, {"text": "9M119M\u70ae\u5c04\u5bfc\u5f39", "offset": 69, "length": 10}]}}, {"sentence": "\u76ee\u524d\uff0c\u591a\u8f86T-90M\u5766\u514b\u5df2\u7ecf\u88ab\u8fd0\u9001\u81f3\u83ab\u65af\u79d1\u9644\u8fd1\u7684\u963f\u62c9\u6bd4\u8bfa\u8bad\u7ec3\u573a\uff0c\u53c2\u52a0\u9605\u5175\u5f69\u6392\uff0c\u5c06\u5728\u4eca\u5e745\u67089\u65e5\u7684\u7ea2\u573a\u80dc\u5229\u65e5\u9605\u5175\u5f0f\u4e0a\u6b63\u5f0f\u516c\u5f00\u4eae\u76f8\u3002", "events": [{"trigger": {"text": "\u6b63\u5f0f\u516c\u5f00\u4eae\u76f8", "offset": 57, "length": 6}, "subject": {"text": "\u591a\u8f86T-90M\u5766\u514b", "offset": 3, "length": 9}, "object": {"text": "\u5728\u4eca\u5e745\u67089\u65e5\u7684\u7ea2\u573a\u80dc\u5229\u65e5\u9605\u5175\u5f0f\u4e0a", "offset": 40, "length": 17}, "labels": {"tense": "\u5176\u4ed6", "polarity": "\u53ef\u80fd"}}, {"trigger": {"text": "\u516c\u5f00\u4eae\u76f8", "offset": 59, "length": 4}, "object": {"text": "", "offset": 0, "length": 0}, "subject": {"text": "", "offset": 0, "length": 0}, "labels": {"tense": "\u5176\u4ed6", "polarity": "\u53ef\u80fd"}}], "arguments": {"time": [{"text": "5\u67089\u65e5", "offset": 43, "length": 4}, {"text": "\u4eca\u5e745\u67089\u65e5", "offset": 41, "length": 6}], "loc": [{"text": "\u963f\u62c9\u6bd4\u8bfa\u8bad\u7ec3\u573a", "offset": 24, "length": 7}, {"text": "\u83ab\u65af\u79d1", "offset": 18, "length": 3}], "country": [], "weapon": [{"text": "T-90M\u5766\u514b", "offset": 5, "length": 7}]}}]