[{"name": "Azua"}, {"name": "Baoruco"}, {"name": "Barahona"}, {"name": "Dajab\u00f3n"}, {"name": "Distrito Nacional"}, {"name": "Duarte"}, {"name": "El\u00edas Pi\u00f1a"}, {"name": "El Seibo"}, {"name": "Espaillat"}, {"name": "Hato Mayor"}, {"name": "Hermanas Mirabal"}, {"name": "Independencia"}, {"name": "La Altagracia"}, {"name": "La Romana"}, {"name": "La Vega"}, {"name": "Mar\u00eda Trinidad S\u00e1nchez"}, {"name": "Monse\u00f1or Nouel"}, {"name": "Monte Cristi"}, {"name": "Monte Plata"}, {"name": "Pedernales"}, {"name": "Peravia"}, {"name": "Puerto Plata"}, {"name": "Saman\u00e1"}, {"name": "S\u00e1nchez Ram\u00edrez"}, {"name": "San Crist\u00f3bal"}, {"name": "San Jos\u00e9 de Ocoa"}, {"name": "San Juan"}, {"name": "San Pedro de Macor\u00eds"}, {"name": "Santiago"}, {"name": "Santiago Rodr\u00edguez"}, {"name": "Santo Domingo"}, {"name": "Valverde"}]