[{"sentence": "\u9a7b\u65e5\u7f8e\u519b\u542f\u52a8\u201c\u5145\u7535\u6869\u201d\u00a0\u51c6\u5907\u8fce\u63a5DDG1000\u4e07\u5428\u5927\u9a71\u8fdb\u9a7b", "events": [], "arguments": {"loc": [], "time": [], "country": [], "weapon": []}}, {"sentence": "\u3010\u73af\u7403\u65f6\u62a5\u7efc\u5408\u62a5\u9053\u3011", "events": [], "arguments": {"loc": [], "time": [], "country": [], "weapon": []}}, {"sentence": "\u636e\u7f8e\u56fd\u300a\u661f\u6761\u65d7\u62a5\u300b1\u670830\u65e5\u62a5\u9053\uff0c\u9a7b\u65e5\u7f8e\u519b\u4f50\u4e16\u4fdd\u57fa\u5730\u5df2\u7ecf\u6b63\u5f0f\u542f\u52a8\u4e86\u4e00\u5ea7\u9ad8\u538b\u4f9b\u7535\u7ad9\u3002", "events": [], "arguments": {"loc": [{"text": "\u4f50\u4e16\u4fdd\u57fa\u5730", "offset": 21, "length": 5}], "time": [{"text": "1\u670830\u65e5", "offset": 9, "length": 5}], "country": [], "weapon": []}}, {"sentence": "\u5b83\u7684\u7279\u522b\u4e4b\u5904\u5728\u4e8e\uff0c\u8fd9\u662f\u4e13\u4e3a\u6700\u65b0\u578b\u201c\u7f8e\u56fd\u201d\u53f7\u4e24\u6816\u653b\u51fb\u8230\u548c\u201c\u6731\u59c6\u6c83\u5c14\u7279\u201d\u7ea7\u9a71\u9010\u8230\u589e\u52a0\u7684\u8f85\u52a9\u8bbe\u65bd\uff0c\u4ece\u800c\u4fdd\u969c\u7f8e\u56fd\u6700\u65b0\u6218\u8230\u80fd\u957f\u671f\u8fdb\u9a7b\u4e1c\u4e9a\u3002", "events": [], "arguments": {"loc": [{"text": "\u4e1c\u4e9a", "offset": 61, "length": 2}], "time": [], "country": [{"text": "\u7f8e\u56fd", "offset": 50, "length": 2}], "weapon": [{"text": "\u201c\u7f8e\u56fd\u201d\u53f7\u4e24\u6816\u653b\u51fb\u8230", "offset": 16, "length": 10}, {"text": "\u201c\u6731\u59c6\u6c83\u5c14\u7279\u201d\u7ea7\u9a71\u9010\u8230", "offset": 27, "length": 11}]}}, {"sentence": "\u62a5\u9053\u79f0\uff0c\u8fd9\u5ea7\u8f93\u7535\u7ad9\u53ef\u4e3a\u505c\u9760\u6e2f\u53e3\u7684\u6218\u8230\u63d0\u4f9b4160\u4f0f\u7684\u9ad8\u538b\u7535\u6d41\u3002", "events": [], "arguments": {"loc": [], "time": [], "country": [], "weapon": []}}, {"sentence": "\u6b64\u524d\u5927\u90e8\u5206\u7f8e\u56fd\u519b\u8230\u505c\u9760\u6e2f\u53e3\u65f6\u53ea\u80fd\u4ece\u7801\u5934\u8f93\u7535\u7ad9\u83b7\u5f97480\u4f0f\u7684\u7535\u529b\uff0c\u6709\u65f6\u4e0d\u5f97\u4e0d\u4e3a\u6b64\u8fde\u63a512\u6839\u7535\u7f06\u3002", "events": [], "arguments": {"loc": [], "time": [], "country": [], "weapon": []}}, {"sentence": "\u968f\u7740\u65b0\u4e00\u4ee3\u201c\u798f\u7279\u201d\u7ea7\u822a\u6bcd\u3001\u201c\u7f8e\u56fd\u201d\u7ea7\u4e24\u6816\u653b\u51fb\u8230\u4ee5\u53ca\u201c\u6731\u59c6\u6c83\u5c14\u7279\u201d\u7ea7\u9a71\u9010\u8230\u7684\u670d\u5f79\uff0c\u5b83\u4eec\u5bf9\u7535\u529b\u4f9b\u5e94\u7684\u8981\u6c42\u66f4\u9ad8\uff0c\u56e0\u6b64\u9700\u8981\u66f4\u5f3a\u5927\u7684\u7801\u5934\u4f9b\u7535\u80fd\u529b\u3002", "events": [], "arguments": {"loc": [], "time": [], "country": [], "weapon": [{"text": "\u201c\u7f8e\u56fd\u201d\u7ea7\u4e24\u6816\u653b\u51fb\u8230", "offset": 13, "length": 10}, {"text": "\u201c\u798f\u7279\u201d\u7ea7\u822a\u6bcd", "offset": 5, "length": 7}, {"text": "\u201c\u6731\u59c6\u6c83\u5c14\u7279\u201d\u7ea7\u9a71\u9010\u8230", "offset": 25, "length": 11}]}}, {"sentence": "\u6b64\u524d\u4e94\u89d2\u5927\u697c\u5df2\u7ecf\u5411\u65e5\u672c\u6d3e\u9063\u4e86\u8bb8\u591a\u6700\u73b0\u4ee3\u5316\u7684\u6b66\u5668\u7cfb\u7edf\uff0c\u5305\u62ec\u7f8e\u56fd\u6d77\u519b\u9646\u6218\u961f\u7684F-35B\u9690\u5f62\u6218\u6597\u673a\u548c\u7a7a\u519b\u7684CV-22\u201c\u9c7c\u9e70\u201d\u503e\u659c\u65cb\u8f6c\u7ffc\u98de\u673a\uff0c\u4f46\u8fd8\u6ca1\u6709\u5728\u90a3\u91cc\u90e8\u7f72\u6700\u65b0\u578b\u9a71\u9010\u8230\u3002", "events": [], "arguments": {"loc": [], "time": [], "country": [], "weapon": [{"text": "F-35B\u9690\u5f62\u6218\u6597\u673a", "offset": 36, "length": 10}, {"text": "CV-22\u201c\u9c7c\u9e70\u201d\u503e\u659c\u65cb\u8f6c\u7ffc\u98de\u673a", "offset": 50, "length": 16}]}}, {"sentence": "\u800c\u65b0\u5efa\u6210\u7684\u9ad8\u538b\u8f93\u7535\u7ad9\u8ba9\u7f8e\u56fd\u6d77\u519b\u8fd9\u4e9b\u65b0\u9510\u6218\u8230\u80fd\u957f\u671f\u4f7f\u7528\u9a7b\u65e5\u57fa\u5730\u3002", "events": [], "arguments": {"loc": [], "time": [], "country": [], "weapon": []}}, {"sentence": "\u7f8e\u56fd\u592a\u5e73\u6d0b\u8230\u961f\u53d1\u8a00\u4eba\u8a79\u59c6\u65af\u00b7\u4e9a\u5f53\u65af\u5bf9\u6b64\u8868\u793a\uff1a\u201c\u7f8e\u56fd\u6d77\u519b\u4e0d\u65ad\u76d1\u6d4b\u90e8\u961f\u7684\u6218\u5907\u548c\u80fd\u529b\uff0c\u4ee5\u63d0\u4f9b\u5c3d\u53ef\u80fd\u6700\u5f3a\u5927\u3001\u6700\u6709\u80fd\u529b\u7684\u6d77\u4e0a\u529b\u91cf\u3002", "events": [], "arguments": {"loc": [], "time": [], "country": [], "weapon": []}}, {"sentence": "\u201d", "events": [], "arguments": {"loc": [], "time": [], "country": [], "weapon": []}}, {"sentence": "\u62a5\u9053\u7279\u522b\u63d0\u5230\uff0c\u4f5c\u4e3a\u7f8e\u56fd\u6d77\u519b\u5f53\u524d\u6700\u65b0\u9510\u7684\u4e3b\u529b\u6218\u8230\u4e4b\u4e00\uff0c\u5916\u5f62\u5145\u6ee1\u79d1\u5e7b\u8272\u5f69\u7684\u201c\u6731\u59c6\u6c83\u5c14\u7279\u201d\u7ea7\u9a71\u9010\u8230\u91c7\u7528\u5148\u8fdb\u7684\u5168\u7535\u63a8\u8fdb\u7cfb\u7edf\u3002", "events": [], "arguments": {"loc": [], "time": [], "country": [], "weapon": []}}, {"sentence": "\u5b83\u9996\u5148\u4f7f\u7528\u71c3\u6c14\u8f6e\u673a\u53d1\u7535\uff0c\u7136\u540e\u9a71\u52a8\u63a8\u8fdb\u7cfb\u7edf\u63d0\u4f9b\u52a8\u529b\u3002", "events": [], "arguments": {"loc": [], "time": [], "country": [], "weapon": []}}, {"sentence": "\u8fd9\u79cd\u8bbe\u8ba1\u4e0d\u4ec5\u51cf\u5c11\u4e86\u53d8\u901f\u7bb1\u548c\u79bb\u5408\u5668\u7b49\u590d\u6742\u673a\u68b0\u88c5\u7f6e\uff0c\u63d0\u9ad8\u7cfb\u7edf\u7684\u7a33\u5b9a\u6027\uff0c\u540c\u65f6\u4e5f\u4e3a\u8230\u4e0a\u529f\u80fd\u65e5\u76ca\u590d\u6742\u7684\u96f7\u8fbe\u7b49\u7535\u5b50\u7cfb\u7edf\u63d0\u4f9b\u5145\u8db3\u7535\u529b\uff0c\u751a\u81f3\u4e3a\u5c06\u6765\u7684\u6fc0\u5149\u6b66\u5668\u63d0\u4f9b\u80fd\u6e90\u3002", "events": [], "arguments": {"loc": [], "time": [], "country": [], "weapon": []}}, {"sentence": "\u4e9a\u5229\u6851\u90a3\u5dde\u7acb\u5927\u5b66\u5e03\u83b1\u767b\u00b7\u827e\u4f26\u6559\u6388\u8ba4\u4e3a\uff0c\u5c3d\u7ba1\u201c\u6731\u59c6\u6c83\u5c14\u7279\u201d\u7ea7\u9a71\u9010\u8230\u6b63\u9762\u4e34\u56f0\u5883\uff0c\u5efa\u9020\u6570\u91cf\u5927\u5e45\u524a\u51cf\uff0c\u4f46\u7f8e\u6d77\u519b\u8230\u8247\u7535\u529b\u5316\u7684\u8d8b\u52bf\u4e0d\u53ef\u6539\u53d8\u3002", "events": [], "arguments": {"loc": [], "time": [], "country": [], "weapon": [{"text": "\u201c\u6731\u59c6\u6c83\u5c14\u7279\u201d\u7ea7\u9a71\u9010\u8230", "offset": 21, "length": 11}]}}, {"sentence": "\u76ee\u524d\u7f8e\u56fd\u672c\u571f\u7684\u5723\u8fed\u6208\u548c\u8bfa\u798f\u514b\u6d77\u519b\u57fa\u5730\u5747\u5df2\u589e\u8bbe\u9ad8\u538b\u8f93\u7535\u7ad9\uff0c\u968f\u7740\u65e5\u672c\u4f50\u4e16\u4fdd\u57fa\u5730\u76f8\u5173\u8bbe\u65bd\u7684\u5b8c\u5584\uff0c\u8fd9\u4e9b\u201c\u7535\u52a8\u8230\u8247\u201d\u5728\u4e1c\u4e9a\u7684\u957f\u671f\u90e8\u7f72\u5c06\u5f97\u5230\u4fdd\u969c\u3002", "events": [], "arguments": {"loc": [], "time": [], "country": [], "weapon": []}}, {"sentence": "\u25b2\uff08\u9648  \u5c71\uff09", "events": [], "arguments": {"loc": [], "time": [], "country": [], "weapon": []}}, {"sentence": "\uff08\u9648  \u5c71\uff09", "events": [], "arguments": {"loc": [], "time": [], "country": [], "weapon": []}}]