[{"sentence": "\u7f8e\u56fd\u65b0\u578b\u9690\u5f62\u6218\u673a\u6302\u8f7d\u795e\u79d8\u88c5\u7f6e\u8bd5\u98de\u00a0\u5916\u5a92\u731c\u4e0e\u6fc0\u5149\u6b66\u5668\u6709\u5173", "events": [], "arguments": {"loc": [], "time": [], "country": [{"text": "\u7f8e\u56fd", "offset": 0, "length": 2}], "weapon": [{"text": "\u65b0\u578b\u9690\u5f62\u6218\u673a", "offset": 2, "length": 6}, {"text": "\u6fc0\u5149\u6b66\u5668", "offset": 21, "length": 4}]}}, {"sentence": "\u3010\u73af\u7403\u7f51\u62a5\u9053 \u8bb0\u8005 \u5f90\u7490\u660e\u3011", "events": [], "arguments": {"loc": [], "time": [], "country": [], "weapon": []}}, {"sentence": "\u7531\u7f8e\u56fdScaled Composites\u516c\u53f8\u7814\u5236\u7684401\u578b\u201c\u6218\u795e\u4e4b\u5b50\u201d\u9690\u5f62\u98de\u673a\u7684\u8fd1\u65e5\u88ab\u62cd\u5230\u6302\u8f7d\u4e86\u4e00\u4e2a\u795e\u79d8\u8bbe\u5907\u8fdb\u884c\u8bd5\u98de\u3002", "events": [{"trigger": {"text": "\u7814\u5236", "offset": 22, "length": 2}, "subject": {"text": "Scaled Composites\u516c\u53f8", "offset": 3, "length": 19}, "object": {"text": "401\u578b\u201c\u6218\u795e\u4e4b\u5b50\u201d\u9690\u5f62\u98de\u673a", "offset": 25, "length": 14}}], "arguments": {"loc": [], "time": [], "country": [{"text": "\u7f8e\u56fd", "offset": 1, "length": 2}], "weapon": []}}, {"sentence": "\u7f8e\u5a92\u5206\u6790\u8ba4\u4e3a\uff0c\u8fd9\u53ef\u80fd\u4e0e\u6fc0\u5149\u6b66\u5668\u6d4b\u8bd5\u6709\u5173\u3002", "events": [], "arguments": {"loc": [], "time": [], "country": [{"text": "\u7f8e", "offset": 0, "length": 1}], "weapon": []}}, {"sentence": "\u62a5\u9053\u79f0\uff0c\u8fd9\u662f\u7f8e\u56fd\u6700\u795e\u79d8\u7684\u9690\u5f62\u98de\u673a\u9a8c\u8bc1\u673a\uff0c\u5728\u6700\u8fd1\u7684\u51e0\u4e2a\u6708\u8fd9\u6b3e\u98de\u673a\u975e\u5e38\u201c\u5fd9\u788c\u201d\uff0c\u4e00\u76f4\u5728\u4e0e\u4e0d\u540c\u7684\u98de\u673a\u8fdb\u884c\u8054\u5408\u6d4b\u8bd5\u3002", "events": [], "arguments": {"loc": [], "time": [], "country": [{"text": "\u7f8e\u56fd", "offset": 6, "length": 2}], "weapon": [{"text": "\u9690\u5f62\u98de\u673a", "offset": 12, "length": 4}]}}, {"sentence": "\u5f53\u4e00\u67b6401\u578b\u201c\u6218\u795e\u4e4b\u5b50\u201d\u9690\u5f62\u98de\u673a\u5728\u83ab\u54c8\u97e6\u822a\u7a7a\u822a\u5929\u6e2f\u964d\u843d\u65f6\uff0c\u88ab\u62cd\u5230\u5728\u673a\u8179\u4e0b\u65b9\u6302\u8f7d\u4e86\u4e00\u4e2a\u201c\u4ee4\u4eba\u8d39\u89e3\u201d\u7684\u65b0\u88c5\u7f6e\u3002", "events": [], "arguments": {"loc": [{"text": "\u83ab\u54c8\u97e6\u822a\u7a7a\u822a\u5929\u6e2f", "offset": 18, "length": 8}], "time": [], "country": [], "weapon": [{"text": "401\u578b\u201c\u6218\u795e\u4e4b\u5b50\u201d\u9690\u5f62\u98de\u673a", "offset": 3, "length": 14}]}}, {"sentence": "\u4ece\u753b\u9762\u4e2d\u53ef\u4ee5\u770b\u5230\uff0c\u8fd9\u67b6401\u578b\u201c\u6218\u795e\u4e4b\u5b50\u201d\u98de\u673a\u7684\u673a\u8179\u4e0b\u65b9\u51fa\u73b0\u770b\u4e86\u4e00\u4e2a\u5916\u5f62\u5947\u7279\u7684\u88c5\u7f6e\u3002", "events": [], "arguments": {"loc": [], "time": [], "country": [], "weapon": [{"text": "401\u578b\u201c\u6218\u795e\u4e4b\u5b50\u201d\u98de\u673a", "offset": 11, "length": 12}]}}, {"sentence": "\u8fd9\u4e00\u88c5\u7f6e\u7684\u524d\u65b9\u770b\u8d77\u6765\u50cf\u662f\u4e00\u4e2a\u8fdb\u6c14\u9053\uff0c\u540e\u65b9\u5219\u50cf\u662f\u4e00\u4e2a\u6392\u6c14\u9053\u3002", "events": [], "arguments": {"loc": [], "time": [], "country": [], "weapon": []}}, {"sentence": "\u62a5\u9053\u8ba4\u4e3a\uff0c\u867d\u7136\u76ee\u524d\u8fd8\u4e0d\u6e05\u695a\u505a\u51fa\u8fd9\u4e00\u6539\u8fdb\u7684\u76ee\u7684\u662f\u4ec0\u4e48\uff0c\u4f46\u8fd9\u6b3e\u98de\u673a\u4f3c\u4e4e\u662f\u5b89\u88c5\u4e86\u4e00\u4e2a\u5927\u578b\u7684\u6563\u70ed\u5668\u548c\u6392\u6c14\u88c5\u7f6e\uff0c\u8fd9\u610f\u5473\u7740401\u578b\u98de\u673a\u5728\u4e0d\u4e45\u7684\u5c06\u6765\u53ef\u80fd\u4f1a\u4f5c\u4e3a\u5b9a\u5411\u80fd\uff08\u6fc0\u5149\uff09\u88c5\u7f6e\u7684\u6d4b\u8bd5\u5e73\u53f0\u3002", "events": [], "arguments": {"loc": [], "time": [], "country": [], "weapon": [{"text": "401\u578b\u98de\u673a", "offset": 55, "length": 6}]}}, {"sentence": "\u62a5\u9053\u79f0\uff0c401\u578b\u201c\u6218\u795e\u4e4b\u5b50\u201d\u98de\u673a\u5c06\u8fdb\u6c14\u9053\u5b89\u88c5\u5728\u673a\u80cc\u4e0a\uff0c\u4f7f\u5f97\u673a\u8179\u8bbe\u5907\u6709\u7740\u76f8\u5f53\u5bbd\u9614\u7684\u201c\u89c6\u91ce\u201d\uff0c\u8fd9\u5bf9\u4e8e\u4f7f\u7528\u5b9a\u5411\u80fd\u6b66\u5668\u548c\u76d1\u89c6\u8bbe\u5907\u90fd\u662f\u6709\u76ca\u7684\u3002", "events": [], "arguments": {"loc": [], "time": [], "country": [], "weapon": [{"text": "401\u578b\u201c\u6218\u795e\u4e4b\u5b50\u201d\u98de\u673a", "offset": 4, "length": 12}]}}, {"sentence": "\u66f4\u91cd\u8981\u7684\u662f\uff0c\u4f7f\u7528\u540a\u8231\u5f0f\u7684\u6fc0\u5149\u88c5\u7f6e\u6709\u4e0d\u5c11\u7f3a\u70b9\uff0c\u4e0d\u4ec5\u89c6\u91ce\u53d7\u9650\uff0c\u8fd8\u9700\u914d\u5907\u72ec\u7acb\u7684\u51b7\u5374\u548c\u8f85\u52a9\u6392\u6c14\u7cfb\u7edf\uff0c\u8fd9\u4e9b\u7cfb\u7edf\u7684\u7528\u7535\u4e5f\u662f\u4e00\u5927\u95ee\u9898\u3002", "events": [], "arguments": {"loc": [], "time": [], "country": [], "weapon": []}}, {"sentence": "\u800c\u5982\u679c\u628a\u5de8\u5927\u7684\u6563\u70ed\u7cfb\u7edf\u76f4\u63a5\u653e\u5728\u8fdb\u6c14\u9053\u7684\u6fc0\u6d41\u4e4b\u4e2d\uff0c\u5e76\u914d\u5907\u4e00\u4e2a\u5355\u72ec\u7684\u7535\u6e90\uff0c\u5c31\u50cf\u73b0\u5728401\u578b\u201c\u6218\u795e\u4e4b\u5b50\u201d\u98de\u673a\u6240\u505a\u7684\u90a3\u6837\uff0c\u662f\u6709\u4e00\u5b9a\u9053\u7406\u7684\u3002", "events": [], "arguments": {"loc": [], "time": [], "country": [], "weapon": [{"text": "401\u578b\u201c\u6218\u795e\u4e4b\u5b50\u201d\u98de\u673a", "offset": 39, "length": 12}]}}, {"sentence": "\u76ee\u524d\u7f8e\u56fd\u6b63\u5728\u63a8\u8fdb\u591a\u4e2a\u673a\u8f7d\u6fc0\u5149\u6b66\u5668\u9879\u76ee\uff0c\u4f8b\u5982\u201c\u81ea\u6211\u4fdd\u62a4\u9ad8\u80fd\u6fc0\u5149\u6f14\u793a\u5668\u201d(SHiELD)\u3002", "events": [], "arguments": {"loc": [], "time": [], "country": [], "weapon": [{"text": "\u201c\u81ea\u6211\u4fdd\u62a4\u9ad8\u80fd\u6fc0\u5149\u6f14\u793a\u5668\u201d(SHiELD)", "offset": 21, "length": 21}]}}, {"sentence": "\u5305\u62ec\u8bfa\u666e\u6d1b\u65af-\u683c\u9c81\u66fc\u516c\u53f8\u5728\u5185\u7684\u8bb8\u591a\u516c\u53f8\u6b63\u5728\u4e0e\u7f8e\u56fd\u7a7a\u519b\u7814\u7a76\u5b9e\u9a8c\u5ba4\u5408\u4f5c\u5f00\u5c55\u9879\u76ee\u7814\u7a76\uff0c\u8bfa\u683c\u516c\u53f8\u8d1f\u8d23\u7814\u53d1\u6ce2\u675f\u63a7\u5236\u7cfb\u7edf\u548c\u6fc0\u5149\u8bbe\u5907\u7684\u5916\u58f3\u3002", "events": [], "arguments": {"loc": [], "time": [], "country": [], "weapon": []}}, {"sentence": "\u6240\u6709\u8fd9\u4e9b\u8bbe\u5907\u90fd\u5fc5\u987b\u53c8\u5c0f\u53c8\u8f7b\uff0c\u80fd\u591f\u88c5\u5230\u6218\u672f\u98de\u673a\u53ef\u4ee5\u643a\u5e26\u7684\u6b66\u5668\u540a\u8231\u4e2d\u3002", "events": [], "arguments": {"loc": [], "time": [], "country": [], "weapon": []}}, {"sentence": "SHiELD\u662f\u4e00\u79cd\u9632\u5fa1\u7cfb\u7edf\uff0c\u4e3b\u8981\u7528\u4e8e\u51fb\u843d\u654c\u673a\u6216\u662f\u6765\u88ad\u5bfc\u5f39\u3002", "events": [], "arguments": {"loc": [], "time": [], "country": [], "weapon": [{"text": "SHiELD", "offset": 0, "length": 6}]}}, {"sentence": "\u53e6\u4e00\u4e2a\u6b63\u5728\u8fdb\u884c\u7684\u673a\u8f7d\u6fc0\u5149\u6b66\u5668\u9879\u76ee\u662f\u8ba1\u5212\u4e8e2022\u5e74\u5b89\u88c5\u5728AC-130\u7a7a\u4e2d\u70ae\u8247\u673a\u4e0a\u768460\u5343\u74e6\u7ea7\u6fc0\u5149\u5668\uff0c\u8be5\u9879\u76ee\u7531\u7f8e\u56fd\u7a7a\u519b\u7279\u79cd\u4f5c\u6218\u53f8\u4ee4\u90e8\u8d1f\u8d23\u3002", "events": [], "arguments": {"loc": [], "time": [{"text": "2022\u5e74", "offset": 20, "length": 5}], "country": [{"text": "\u7f8e\u56fd", "offset": 54, "length": 2}], "weapon": [{"text": "AC-130\u7a7a\u4e2d\u70ae\u8247\u673a", "offset": 28, "length": 11}]}}]